multibot/__init__.py
multibot/constants.py
multibot/exceptions.py
multibot/bots/__init__.py
multibot/bots/discord_bot.py
multibot/bots/multi_bot.py
multibot/bots/telegram_bot.py
multibot/bots/twitch_bot.py
multibot/models/__init__.py
multibot/models/buttons.py
multibot/models/chat.py
multibot/models/enums.py
multibot/models/event_component.py
multibot/models/message.py
multibot/models/penalties.py
multibot/models/registered_callback.py
multibot/models/role.py
multibot/models/user.py
multibot-1.9.3.dist-info/LICENSE
multibot-1.9.3.dist-info/METADATA
multibot-1.9.3.dist-info/WHEEL
multibot-1.9.3.dist-info/top_level.txt
multibot-1.9.3.dist-info/RECORD
