Metadata-Version: 2.1
Name: multibot
Version: 1.9.3
Summary: Platform agnostic high-level bot infrastructure. Develop one bot and you will have three: one for Discord, another one for Telegram and another one for Twitch. All bots use the same objects and logic.  For now there are adapters for three platforms but more may be added in the future.
Home-page: https://github.com/AlberLC/multibot
Author: AlberLC
Project-URL: Bug Tracker, https://github.com/AlberLC/multibot/issues
Classifier: Programming Language :: Python :: 3.10
Classifier: License :: OSI Approved :: MIT License
Classifier: Operating System :: OS Independent
Requires-Python: >=3.10
License-File: LICENSE
Requires-Dist: cryptg
Requires-Dist: discord.py
Requires-Dist: flanautils
Requires-Dist: hachoir
Requires-Dist: pillow
Requires-Dist: pymongo
Requires-Dist: telethon
Requires-Dist: twitchio
